Workbook

Sheet Anamnese
A1: ANAMNESE FINANCEIRA - A.D. FINANCE
A3: Consultor | B3: Alessandro Dória Alves Pereira
A4: CRA | B4: 01-066451/D
A6: Nome Completo | C6: Alessandro Dória
A7: CPF | C7: 040.842.356-01
A8: Data Nascimento | C8: 28705
A9: Estado Civil | C9: Casado
A10: Profissao | C10: Administrador
A11: Empresa | C11: Autônomo
A12: Telefone | C12: 031 98578-5744
A13: Email | C13: adoria19.adm@gmail.com
A14: Objetivo Principal | C14: Independência Financeira

Sheet Renda
A2: Salario | B2: 3200
A3: Prolabore
A4: Alugueis
A5: Investimentos
A6: Outros
A8: Renda Total | B8: =SUM(B2:B6) -> 3200

Sheet Despesas
A2: Moradia | B2: 1500 | D2: Meses Reserva | E2: 12
A3: Alimentacao | B3: 700 | D3: Reserva Necessaria | E3: =B9*E2 -> 31200
A4: Transporte | B4: 400
A5: Saude
A6: Educacao
A7: Outras
A9: Despesa Total | B9: =SUM(B2:B7) -> 2600

Sheet Patrimonio
A2: Imoveis | B2: 100000
A3: Veiculos | B3: 35000
A4: Outros
A6: Patrimonio Bruto | B6: =SUM(B2:B4) -> 135000

Sheet Dividas
A2: Cartao | B2: 2600
A3: Emprestimos | B3: 35000
A4: Financiamentos | B4: 5000
A5: Outras
A7: Dividas Totais | B7: =SUM(B2:B5) -> 42600

Sheet Investimentos
A9: Patrimonio Investido | B9: 0

Sheet Plano_Acao
A1: Ação | B1: Responsável | C1: Prazo | D1: Concluída
A2: Controlar Gastos com o Cartão de Crédito | B2: Alessandro | C2: Até Dezembro de 2026 | D2: ☐
A3: Resolver Dívidas com Bancos | B3: Alessandro | C3: 5 anos | D3: ☐
A4: Eliminar Compras Impulsivas | B4: Alessandro | C4: Daqui a 1 Mês | D4: ☐
A5: Eliminar Gastos Supérfluos | B5: Alessandro | C5: Daqui a 1 Mês | D5: ☐
A6: Investimento Pessoal | B6: Alessandro | C6: Á Partir de Dezembro de 2026 | D6: ☐
A7: Projeto Casa Nova | B7: Alessandro | C7: Á Partir de Dezembro de 2026 | D7: ☐
A8: Projeto Carro Novo | B8: Alessandro | C8: Á Partir de Dezembro de 2026 | D8: ☐
A9: Empreendimento | B9: Alessandro | C9: Á Partir de Novembro de 2026 | D9: ☐
A10: Reserva de Emergência | B10: Alessandro | C10: Daqui a 3 Meses | D10: ☐
A11: Investimento do Negócio | B11: Alessandro | C11: Á Partir de Novembro de 2026 | D11: ☐

Sheet Laudo
A2: Endividamento | B2: =IF(Renda!B8=0,0,Dividas!B7/Renda!B8) -> 13.3125 | D2: Score AD | E2: =MAX(0,MIN(100,100-(B2*30)+(B3*10)+(B4*30)+(B5*5))) -> 0
A3: Liquidez | B3: =IF(Despesas!B9=0,0,Investimentos!B9/Despesas!B9) -> 0 | D3: Classificacao | E3: =IF(E2>=90,"Diamante",IF(E2>=75,"Ouro",IF(E2>=60,"Prata",IF(E2>=40,"Bronze","Reconstrucao")))) -> Reconstrucao
A4: Capacidade Poupanca | B4: =IF(Renda!B8=0,0,(Renda!B8-Despesas!B9)/Renda!B8) -> 0.1875
A5: Reserva Emergencia | B5: =IF(Despesas!B9=0,0,Despesas!E3/Despesas!B9) -> 12
A6: Investimentos | B6: =Investimentos!B9 -> 0
A7: Patrimonio | B7: =Patrimonio!B6-Dividas!B7 -> 92400

Sheet Parametros

Sheet Dashboard
A1: A.D. FINANCE Dashboard Executivo
D2: Semaforo Risco
D3: =IF(Laudo!E2>=75,"VERDE",IF(Laudo!E2>=50,"AMARELO","VERMELHO")) -> VERMELHO
A4: Renda | B4: =Renda!B8 -> 3200
A5: Despesas | B5: =Despesas!B9 -> 2600
A6: Reserva | B6: =Despesas!E3 -> 31200
A7: Dividas | B7: =Dividas!B7 -> 42600
A8: Patrimonio Liquido | B8: =Laudo!B7 -> 92400
A9: Score | B9: =Laudo!E2 -> 0
A12: Endividamento | B12: =Laudo!B2 -> 13.3125
A13: Liquidez | B13: =Laudo!B3 -> 0
A14: Capacidade Poupanca | B14: =Laudo!B4 -> 0.1875
A15: Reserva Emergencia | B15: =Laudo!B5 -> 12
A16: Investimentos | B16: =Laudo!B6 -> 0
A17: Patrimonio | B17: =Laudo!B7 -> 92400
